qhdl/__init__.py
qhdl-0.1.0.dist-info/DESCRIPTION.rst
qhdl-0.1.0.dist-info/METADATA
qhdl-0.1.0.dist-info/RECORD
qhdl-0.1.0.dist-info/WHEEL
qhdl-0.1.0.dist-info/metadata.json
qhdl-0.1.0.dist-info/top_level.txt
