Metadata-Version: 2.0
Name: qhdl
Version: 0.1.0
Summary: Circuit Components as and QHDL in Python
Home-page: https://github.com/mabuchilab/qhdl
Author: Michael Goerz
Author-email: mail@michaelgoerz.net
License: MIT license
Keywords: qhdl
Platform: UNKNOWN
Classifier: Development Status :: 2 - Pre-Alpha
Classifier: Intended Audience :: Developers
Classifier: License :: OSI Approved :: MIT License
Classifier: Natural Language :: English
Classifier: Programming Language :: Python :: 3.5
Classifier: Programming Language :: Python :: 3.6
Classifier: Programming Language :: Python :: 3.7
Provides-Extra: dev
Provides-Extra: dev
Requires-Dist: coverage; extra == 'dev'
Requires-Dist: pytest; extra == 'dev'
Requires-Dist: pytest-cov; extra == 'dev'
Requires-Dist: pytest-xdist; extra == 'dev'
Requires-Dist: twine; extra == 'dev'
Requires-Dist: pep8; extra == 'dev'
Requires-Dist: flake8; extra == 'dev'
Requires-Dist: wheel; extra == 'dev'
Requires-Dist: sphinx; extra == 'dev'
Requires-Dist: sphinx-autobuild; extra == 'dev'
Requires-Dist: sphinx-rtd-theme; extra == 'dev'
Requires-Dist: sphinx-autodoc-typehints; extra == 'dev'
Requires-Dist: gitpython; extra == 'dev'
Requires-Dist: better-apidoc; extra == 'dev'
Requires-Dist: jupyter; extra == 'dev'
Requires-Dist: nbval; extra == 'dev'
Requires-Dist: nbsphinx; extra == 'dev'
Requires-Dist: watermark; extra == 'dev'
